cardscraper/__init__.py
cardscraper/__main__.py
cardscraper/__version__.py
cardscraper/config.py
cardscraper/generate.py
cardscraper/template.py
cardscraper/default/__init__.py
cardscraper/default/deck.py
cardscraper/default/model.py
cardscraper/default/package.py
cardscraper/default/scraping.py
cardscraper-0.4.2.dist-info/METADATA
cardscraper-0.4.2.dist-info/WHEEL
cardscraper-0.4.2.dist-info/entry_points.txt
cardscraper-0.4.2.dist-info/licenses/LICENSE
cardscraper-0.4.2.dist-info/RECORD
