Metadata-Version: 2.1
Name: cardscraper
Version: 0.4.2
Summary: A tool for generating Anki cards by web scraping
Project-URL: Homepage, https://github.com/sakhezech/cardscraper
License: MIT License
License-File: LICENSE
Requires-Dist: beautifulsoup4
Requires-Dist: genanki
Requires-Dist: pyyaml
Requires-Dist: requests
